MANIFEST.in
README.md
requirements.txt
setup.cfg
setup.py
src/LICENSE.txt
src/TODO.txt
src/docxsphinx/__init__.py
src/docxsphinx/builder.py
src/docxsphinx/writer.py
src/docxsphinx.egg-info/PKG-INFO
src/docxsphinx.egg-info/SOURCES.txt
src/docxsphinx.egg-info/dependency_links.txt
src/docxsphinx.egg-info/entry_points.txt
src/docxsphinx.egg-info/not-zip-safe
src/docxsphinx.egg-info/requires.txt
src/docxsphinx.egg-info/top_level.txt