Metadata-Version: 2.1
Name: docxsphinx
Version: 1.0.0
Summary: Sphinx docx builder extension.
Home-page: https://github.com/mherkazandjian/docxsphinx
Author: Mher Kazandjian, Hugo Buddelmeijer
Author-email: mherkazandjian@gmail.com, hugo@buddelmeijer.nl
License: MIT
Keywords: sphinx,extension,builder,docx,OpenXML
Platform: UNKNOWN
Classifier: Development Status :: 5 - Production/Stable
Classifier: Programming Language :: Python :: 3
Classifier: Intended Audience :: System Administrators
Classifier: Intended Audience :: Developers
Classifier: Intended Audience :: Science/Research
Classifier: License :: OSI Approved :: MIT License
Classifier: Programming Language :: Python
Classifier: Topic :: Office/Business :: Office Suites
Classifier: Topic :: Software Development :: Documentation
Classifier: Topic :: Text Processing :: Markup
Provides-Extra: test
